moonlabel/__init__.py
moonlabel/coco.py
moonlabel/dataset.py
moonlabel/infer.py
moonlabel/types.py
moonlabel/utils.py
moonlabel/voc.py
moonlabel/yolo.py
moonlabel/server/__init__.py
moonlabel/server/api.py
moonlabel/server/cli.py
moonlabel/server/static/index.html
moonlabel/server/static/assets/index-WyKY3o_5.css
moonlabel/server/static/assets/index-ozv8hWk5.js
moonlabel/server/static/assets/moonlabellogo-BPx9MdO3.svg
moonlabel-0.1.5.dist-info/licenses/LICENSE
moonlabel-0.1.5.dist-info/METADATA
moonlabel-0.1.5.dist-info/WHEEL
moonlabel-0.1.5.dist-info/entry_points.txt
moonlabel-0.1.5.dist-info/top_level.txt
moonlabel-0.1.5.dist-info/RECORD
