Metadata-Version: 2.4
Name: moonlabel
Version: 0.1.5
Summary: Create object-detection datasets (YOLO) using Moondream
Author: Muratcan Laloğlu
License-Expression: Apache-2.0
Project-URL: Homepage, https://github.com/muratcanlaloglu/moonlabel
Project-URL: Source, https://github.com/muratcanlaloglu/moonlabel
Requires-Python: >=3.11
License-File: LICENSE
Requires-Dist: moondream
Requires-Dist: Pillow
Requires-Dist: tqdm>=4.66.0
Provides-Extra: local
Requires-Dist: transformers>=4.40.0; extra == "local"
Requires-Dist: torch>=2.2.0; extra == "local"
Requires-Dist: accelerate; extra == "local"
Requires-Dist: einops; extra == "local"
Requires-Dist: pyvips-binary; extra == "local"
Requires-Dist: pyvips; extra == "local"
Provides-Extra: ui
Requires-Dist: fastapi[standard]; extra == "ui"
Dynamic: license-file
